SmoobuExtractorFormatter/__init__.py
SmoobuExtractorFormatter/smoobuOutput.py
SmoobuExtractorFormatter-1.0.6.dist-info/LICENSE.txt
SmoobuExtractorFormatter-1.0.6.dist-info/METADATA
SmoobuExtractorFormatter-1.0.6.dist-info/WHEEL
SmoobuExtractorFormatter-1.0.6.dist-info/top_level.txt
SmoobuExtractorFormatter-1.0.6.dist-info/RECORD
