Metadata-Version: 2.1
Name: SmoobuExtractorFormatter
Version: 1.0.6
Summary: A library to format the output of the Smoobu application
Home-page: UNKNOWN
Author: Badji Rayane
Author-email: rayanebadji.freelance@gmail.com
License: MIT
Keywords: Smoobu
Platform: UNKNOWN
Classifier: Development Status :: 5 - Production/Stable
Classifier: Intended Audience :: Developers
Classifier: Operating System :: OS Independent
Classifier: License :: OSI Approved :: MIT License
Classifier: Programming Language :: Python :: 3
License-File: LICENSE.txt
Requires-Dist: pandas
Requires-Dist: numpy
Requires-Dist: openpyxl
Requires-Dist: xlrd
Requires-Dist: requests
Requires-Dist: unidecode
